simple_symbolic_robotics/__init__.py
simple_symbolic_robotics-0.1.1.dist-info/LICENSE
simple_symbolic_robotics-0.1.1.dist-info/METADATA
simple_symbolic_robotics-0.1.1.dist-info/WHEEL
simple_symbolic_robotics-0.1.1.dist-info/top_level.txt
simple_symbolic_robotics-0.1.1.dist-info/RECORD
