Metadata-Version: 2.1
Name: simple-symbolic-robotics
Version: 0.1.1
Summary: Helper functions for fundamental robotics
Home-page: https://github.com/AdoHaha/simple_symbolic_robotics
Author: Igor Zubrycki
Author-email: igorzubrycki@gmail.com
License: UNKNOWN
Platform: UNKNOWN
Classifier: Programming Language :: Python :: 3
Classifier: License :: OSI Approved :: MIT License
Classifier: Operating System :: OS Independent
Requires-Dist: numpy
Requires-Dist: scipy
Requires-Dist: sympy
